[
  {
    "repo": "libqeep",
    "workflows": [
      {
        "file": "cicd_build_api.yml",
        "name": "libqeep_build_api",
        "github_link": "https://github.com/quantropi/libqeep/actions/workflows/cicd_build_api.yml"
      }
    ]
  },
  {
    "repo": "sdk_qa",
    "workflows": [
      {
        "file": "libqeep.yml",
        "name": "libqeep_qa_test",
        "github_link": "https://github.com/quantropi/sdk_qa/actions/workflows/libqeep.yml"
      },
      {
        "file": "masq_bn.yml",
        "name": "masq_bn_qa_test",
        "github_link": "https://github.com/quantropi/sdk_qa/actions/workflows/masq_bn.yml"
      }
    ]
  }
]